{
  "candidates": [
    {
      "box_xyxy": [
        56.69136428833008,
        77.61813354492188,
        63.3483772277832,
        85.14491271972656
      ],
      "clip_score": 0.0,
      "det_score": 0.4936078190803528,
      "fused_2d_score": 0.4936078190803528,
      "image_crop_path": null,
      "metadata": {
        "detector_metadata": {
          "model_id": "IDEA-Research/grounding-dino-tiny"
        },
        "detector_source": "transformers_groundingdino",
        "skip_clip": true
      },
      "phrase": "red cube",
      "rank": 0,
      "source": "detector_only"
    },
    {
      "box_xyxy": [
        63.527183532714844,
        79.49281311035156,
        69.38018035888672,
        86.23660278320312
      ],
      "clip_score": 0.0,
      "det_score": 0.4913540780544281,
      "fused_2d_score": 0.4913540780544281,
      "image_crop_path": null,
      "metadata": {
        "detector_metadata": {
          "model_id": "IDEA-Research/grounding-dino-tiny"
        },
        "detector_source": "transformers_groundingdino",
        "skip_clip": true
      },
      "phrase": "red cube",
      "rank": 1,
      "source": "detector_only"
    }
  ],
  "clip_prompts": [
    "red cube",
    "red block"
  ],
  "parameters": {
    "clip_model_name": "ViT-B-32",
    "clip_pretrained": "laion2b_s34b_b79k",
    "clip_weight": 0.5,
    "detector_weight": 0.5,
    "skip_clip": true
  }
}